tests/__init__.py
tests/test_vagrant_debian.py
vagrant_debian/__init__.py
vagrant_debian/__main__.py
vagrant_debian/vagrant_debian.py
vagrant_debian/templates/Vagrantfile
vagrant_debian/templates/debian_vm.ovf
vagrant_debian/templates/isolinux.cfg
vagrant_debian/templates/preseed.cfg
vagrant_debian-1.0.9.data/data/share/vagrant_debian/README.md
vagrant_debian-1.0.9.dist-info/AUTHORS.md
vagrant_debian-1.0.9.dist-info/LICENSE
vagrant_debian-1.0.9.dist-info/METADATA
vagrant_debian-1.0.9.dist-info/WHEEL
vagrant_debian-1.0.9.dist-info/entry_points.txt
vagrant_debian-1.0.9.dist-info/top_level.txt
vagrant_debian-1.0.9.dist-info/RECORD
