Metadata-Version: 2.1
Name: vagrant-debian
Version: 1.0.9
Summary: Create vagrant virtualbox from Debian ISO cd
Home-page: https://github.com/apiou/vagrant-debian
Author: Stephane APIOU
Author-email: stephane@apiou.org
License: BSD-2
Platform: Linux
Classifier: Development Status :: 5 - Production/Stable
Classifier: Environment :: Console
Classifier: Intended Audience :: Developers
Classifier: License :: OSI Approved :: BSD License
Classifier: Operating System :: POSIX :: Linux
Classifier: Programming Language :: Python
Classifier: Programming Language :: Python :: 3
Classifier: Programming Language :: Python :: 3.6
Classifier: Programming Language :: Python :: 3.7
Classifier: Programming Language :: Python :: 3.8
Classifier: Programming Language :: Python :: 3.9
Classifier: Topic :: System :: Systems Administration
Classifier: Topic :: System :: Operating System
Classifier: Topic :: Utilities
Requires-Python: >=3.6.0
Requires-Dist: jinja2
Requires-Dist: wheel
Requires-Dist: babel
